[{"id": 2, "day": 10, "name": "\u5927\u96c1\u5854", "x": 108.964174, "y": 34.218263, "drive": 50, "walking": 70, "nature": 20, "human": 80, "hot_on_net": 90, "cold_on_net": 0, "historic": 90, "modern": 0, "price": 0, "entertainment": 40}, {"id": 3, "day": 10, "name": "\u5c0f\u96c1\u5854", "x": 108.942, "y": 34.2392, "drive": 50, "walking": 70, "nature": 20, "human": 80, "hot_on_net": 90, "cold_on_net": 0, "historic": 90, "modern": 0, "price": 0, "entertainment": 40}, {"id": 4, "day": 10, "name": "\u5927\u5510\u8299\u84c9\u56ed", "x": 108.97386, "y": 34.21252, "drive": 40, "walking": 90, "nature": 60, "human": 80, "hot_on_net": 80, "cold_on_net": 0, "historic": 50, "modern": 20, "price": 70, "entertainment": 60}, {"id": 5, "day": 10, "name": "\u79e6\u59cb\u7687\u5175\u9a6c\u4fd1\u535a\u7269\u9986", "x": 109.281574, "y": 34.383714, "drive": 70, "walking": 60, "nature": 20, "human": 90, "hot_on_net": 90, "cold_on_net": 0, "historic": 90, "modern": 0, "price": 80, "entertainment": 20}, {"id": 6, "day": 40, "name": "\u5510\u534e\u6e05\u5bab", "x": 109.21316, "y": 34.363595, "drive": 70, "walking": 70, "nature": 30, "human": 70, "hot_on_net": 30, "cold_on_net": 0, "historic": 70, "modern": 0, "price": 60, "entertainment": 10}, {"id": 7, "day": 20, "name": "\u897f\u5b89\u534a\u5761\u535a\u7269\u9986", "x": 109.05118, "y": 34.27324, "drive": 70, "walking": 70, "nature": 10, "human": 70, "hot_on_net": 20, "cold_on_net": 50, "historic": 20, "modern": 60, "price": 20, "entertainment": 20}, {"id": 8, "day": 20, "name": "\u897f\u5b89\u57ce\u5899", "x": 108.947035, "y": 34.251834, "drive": 0, "walking": 100, "nature": 10, "human": 70, "hot_on_net": 30, "cold_on_net": 0, "historic": 70, "modern": 10, "price": 40, "entertainment": 40}, {"id": 9, "day": 30, "name": "\u9655\u897f\u5386\u53f2\u535a\u7269\u9986", "x": 108.947035, "y": 34.251834, "drive": 20, "walking": 40, "nature": 0, "human": 80, "hot_on_net": 40, "cold_on_net": 0, "historic": 70, "modern": 50, "price": 20, "entertainment": 10}, {"id": 10, "day": 50, "name": "\u6731\u96c0\u56fd\u5bb6\u68ee\u6797\u516c\u56ed", "x": 108.599039, "y": 33.820235, "drive": 90, "walking": 10, "nature": 80, "human": 20, "hot_on_net": 10, "cold_on_net": 70, "historic": 20, "modern": 20, "price": 40, "entertainment": 0}, {"id": 12, "day": 20, "name": "\u56de\u6c11\u8857", "x": 108.93267, "y": 34.26611, "drive": 10, "walking": 80, "nature": 0, "human": 80, "hot_on_net": 80, "cold_on_net": 0, "historic": 0, "modern": 50, "price": 20, "entertainment": 60}, {"id": 14, "day": 20, "name": "\u5b89\u8fdc\u95e8", "x": 108.947181, "y": 34.276058, "drive": 30, "walking": 70, "nature": 20, "human": 80, "hot_on_net": 30, "cold_on_net": 70, "historic": 100, "modern": 0, "price": 0, "entertainment": 0}, {"id": 15, "day": 50, "name": "\u897f\u5b89\u79e6\u5cad\u91ce\u751f\u52a8\u7269\u56ed", "x": 108.86635, "y": 34.047534, "drive": 70, "walking": 40, "nature": 50, "human": 70, "hot_on_net": 70, "cold_on_net": 0, "historic": 20, "modern": 60, "price": 65, "entertainment": 50}, {"id": 16, "day": 20, "name": "\u66f2\u6c5f\u5bd2\u7a91\u9057\u5740\u516c\u56ed", "x": 108.99169, "y": 34.19877, "drive": 20, "walking": 70, "nature": 10, "human": 70, "hot_on_net": 20, "cold_on_net": 60, "historic": 40, "modern": 40, "price": 30, "entertainment": 10}, {"id": 17, "day": 30, "name": "\u897f\u5b89\u6d50\u705e\u56fd\u5bb6\u6e7f\u5730\u516c\u56ed ", "x": 109.00393, "y": 34.41457, "drive": 90, "walking": 0, "nature": 80, "human": 20, "hot_on_net": 30, "cold_on_net": 60, "historic": 0, "modern": 50, "price": 70, "entertainment": 50}, {"id": 18, "day": 20, "name": "\u897f\u5b89\u4e8b\u53d8\u7eaa\u5ff5\u9986-\u5f20\u5b66\u826f\u5c06\u519b\u516c\u9986", "x": 108.967571, "y": 34.257201, "drive": 20, "walking": 60, "nature": 0, "human": 80, "hot_on_net": 30, "cold_on_net": 70, "historic": 60, "modern": 30, "price": 30, "entertainment": 0}, {"id": 19, "day": 20, "name": "\u6d12\u91d1\u6865", "x": 108.93267, "y": 34.26611, "drive": 20, "walking": 70, "nature": 0, "human": 60, "hot_on_net": 60, "cold_on_net": 60, "historic": 0, "modern": 60, "price": 50, "entertainment": 20}, {"id": 20, "day": 50, "name": "\u7ec8\u5357\u5c71", "x": 109.0328, "y": 33.93003, "drive": 90, "walking": 10, "nature": 60, "human": 60, "hot_on_net": 20, "cold_on_net": 60, "historic": 50, "modern": 0, "price": 50, "entertainment": 0}, {"id": 21, "day": 50, "name": "\u592a\u5e73\u56fd\u5bb6\u68ee\u6797\u516c\u56ed", "x": 108.65984, "y": 33.92188, "drive": 80, "walking": 20, "nature": 80, "human": 20, "hot_on_net": 60, "cold_on_net": 60, "historic": 0, "modern": 0, "price": 30, "entertainment": 40}, {"id": 22, "day": 30, "name": "\u66f2\u6c5f\u6d77\u6d0b\u6781\u5730\u516c\u56ed", "x": 108.980484, "y": 34.215302, "drive": 40, "walking": 60, "nature": 0, "human": 70, "hot_on_net": 50, "cold_on_net": 0, "historic": 0, "modern": 70, "price": 50, "entertainment": 70}, {"id": 23, "day": 20, "name": "\u5927\u660e\u5bab\u9057\u5740\u535a\u7269\u9986", "x": 108.96468, "y": 34.28855, "drive": 40, "walking": 60, "nature": 20, "human": 80, "hot_on_net": 40, "cold_on_net": 60, "historic": 100, "modern": 0, "price": 50, "entertainment": 0}, {"id": 24, "day": 40, "name": "\u767d\u9e7f\u539f\u00b7\u767d\u9e7f\u4ed3", "x": 109.114344, "y": 34.218213, "drive": 70, "walking": 60, "nature": 40, "human": 70, "hot_on_net": 80, "cold_on_net": 40, "historic": 20, "modern": 40, "price": 20, "entertainment": 50}, {"id": 25, "day": 20, "name": "\u9655\u897f\u7701\u56fe\u4e66\u9986", "x": 108.945687, "y": 34.231395, "drive": 40, "walking": 60, "nature": 0, "human": 60, "hot_on_net": 10, "cold_on_net": 70, "historic": 0, "modern": 50, "price": 0, "entertainment": 0}, {"id": 26, "day": 40, "name": "\u5c0f\u5be8", "x": 108.946696, "y": 34.222819, "drive": 20, "walking": 90, "nature": 10, "human": 60, "hot_on_net": 80, "cold_on_net": 0, "historic": 0, "modern": 70, "price": 70, "entertainment": 90}, {"id": 27, "day": 20, "name": "\u9655\u897f\u5e08\u8303\u5927\u5b66", "x": 108.891738, "y": 34.153432, "drive": 40, "walking": 70, "nature": 0, "human": 80, "hot_on_net": 20, "cold_on_net": 60, "historic": 0, "modern": 60, "price": 10, "entertainment": 40}, {"id": 28, "day": 30, "name": "\u6c38\u5174\u574a", "x": 108.970121, "y": 34.264836, "drive": 10, "walking": 80, "nature": 30, "human": 50, "hot_on_net": 50, "cold_on_net": 20, "historic": 20, "modern": 40, "price": 50, "entertainment": 70}, {"id": 29, "day": 40, "name": "\u6ca3\u5cea\u53e3", "x": 108.80352, "y": 34.03288, "drive": 80, "walking": 30, "nature": 60, "human": 0, "hot_on_net": 30, "cold_on_net": 50, "historic": 0, "modern": 0, "price": 20, "entertainment": 50}, {"id": 30, "day": 30, "name": "\u66f2\u6c5f\u4e66\u57ce", "x": 108.976559, "y": 34.208709, "drive": 60, "walking": 80, "nature": 30, "human": 50, "hot_on_net": 50, "cold_on_net": 20, "historic": 20, "modern": 50, "price": 50, "entertainment": 50}, {"id": 31, "day": 20, "name": "\u5367\u9f99\u5bfa", "x": 108.71785, "y": 33.95411, "drive": 10, "walking": 90, "nature": 40, "human": 60, "hot_on_net": 0, "cold_on_net": 80, "historic": 80, "modern": 0, "price": 0, "entertainment": 0}, {"id": 32, "day": 30, "name": "\u9a8a\u5c71\u56fd\u5bb6\u68ee\u6797\u516c\u56ed", "x": 109.212221, "y": 34.352943, "drive": 60, "walking": 80, "nature": 70, "human": 50, "hot_on_net": 50, "cold_on_net": 20, "historic": 70, "modern": 50, "price": 50, "entertainment": 50}, {"id": 34, "day": 20, "name": "\u5174\u5e86\u5bab\u516c\u56ed", "x": 108.9344215393, "y": 34.2436656818, "drive": 30, "walking": 60, "nature": 20, "human": 60, "hot_on_net": 10, "cold_on_net": 40, "historic": 10, "modern": 20, "price": 0, "entertainment": 40}, {"id": 35, "day": 30, "name": "\u897f\u5b89\u4ea4\u901a\u5927\u5b66", "x": 108.983696, "y": 34.246259, "drive": 20, "walking": 80, "nature": 50, "human": 70, "hot_on_net": 50, "cold_on_net": 20, "historic": 60, "modern": 70, "price": 20, "entertainment": 50}, {"id": 36, "day": 40, "name": "\u767d\u9e7f\u539f\u6ed1\u96ea\u573a", "x": 109.094681, "y": 34.216398, "drive": 40, "walking": 60, "nature": 20, "human": 60, "hot_on_net": 60, "cold_on_net": 20, "historic": 0, "modern": 70, "price": 60, "entertainment": 80}, {"id": 37, "day": 20, "name": "\u897f\u5317\u5de5\u4e1a\u5927\u5b66", "x": 108.915267, "y": 34.244428, "drive": 60, "walking": 60, "nature": 20, "human": 80, "hot_on_net": 20, "cold_on_net": 40, "historic": 20, "modern": 70, "price": 20, "entertainment": 30}, {"id": 38, "day": 10, "name": "\u5927\u5510\u4e0d\u591c\u57ce", "x": 108.96515, "y": 34.210217, "drive": 20, "walking": 80, "nature": 50, "human": 80, "hot_on_net": 50, "cold_on_net": 20, "historic": 60, "modern": 70, "price": 5, "entertainment": 60}, {"id": 39, "day": 20, "name": "\u5927\u51b0\u7684\u5c0f\u5c4b", "x": 108.94536, "y": 34.25218, "drive": 20, "walking": 40, "nature": 20, "human": 20, "hot_on_net": 80, "cold_on_net": 20, "historic": 20, "modern": 40, "price": 6, "entertainment": 60}]